ultraplot/__init__.py
ultraplot/_version.py
ultraplot/colors.py
ultraplot/config.py
ultraplot/constructor.py
ultraplot/demos.py
ultraplot/figure.py
ultraplot/gridspec.py
ultraplot/legend.py
ultraplot/proj.py
ultraplot/scale.py
ultraplot/ticker.py
ultraplot/ui.py
ultraplot/utils.py
ultraplot/axes/__init__.py
ultraplot/axes/base.py
ultraplot/axes/cartesian.py
ultraplot/axes/geo.py
ultraplot/axes/plot.py
ultraplot/axes/polar.py
ultraplot/axes/shared.py
ultraplot/axes/three.py
ultraplot/axes/plot_types/__init__.py
ultraplot/axes/plot_types/curved_quiver.py
ultraplot/cmaps/Algae.rgb
ultraplot/cmaps/Amp.rgb
ultraplot/cmaps/BR.rgb
ultraplot/cmaps/Balance.rgb
ultraplot/cmaps/Blues1_r.xml
ultraplot/cmaps/Blues2.xml
ultraplot/cmaps/Blues3.xml
ultraplot/cmaps/Blues4_r.xml
ultraplot/cmaps/Blues5.xml
ultraplot/cmaps/Blues6.xml
ultraplot/cmaps/Blues7.xml
ultraplot/cmaps/Blues8.xml
ultraplot/cmaps/Blues9.xml
ultraplot/cmaps/Boreal.json
ultraplot/cmaps/Browns1.xml
ultraplot/cmaps/Browns2.xml
ultraplot/cmaps/Browns3.xml
ultraplot/cmaps/Browns4.xml
ultraplot/cmaps/Browns5.xml
ultraplot/cmaps/Browns6.xml
ultraplot/cmaps/Browns7.xml
ultraplot/cmaps/Browns8.xml
ultraplot/cmaps/Browns9.xml
ultraplot/cmaps/ColdHot.rgb
ultraplot/cmaps/Crest.rgb
ultraplot/cmaps/Curl.rgb
ultraplot/cmaps/Deep.rgb
ultraplot/cmaps/Delta.rgb
ultraplot/cmaps/Dense.rgb
ultraplot/cmaps/Div.json
ultraplot/cmaps/DryWet.json
ultraplot/cmaps/Dusk.json
ultraplot/cmaps/Fire.json
ultraplot/cmaps/Flare.rgb
ultraplot/cmaps/Glacial.json
ultraplot/cmaps/Greens1_r.xml
ultraplot/cmaps/Greens2.xml
ultraplot/cmaps/Greens3_r.xml
ultraplot/cmaps/Greens4.xml
ultraplot/cmaps/Greens5.xml
ultraplot/cmaps/Greens6_r.xml
ultraplot/cmaps/Greens7.xml
ultraplot/cmaps/Greens8.xml
ultraplot/cmaps/Haline.rgb
ultraplot/cmaps/Ice.rgb
ultraplot/cmaps/IceFire.rgb
ultraplot/cmaps/Mako.rgb
ultraplot/cmaps/Marine.json
ultraplot/cmaps/Matter.rgb
ultraplot/cmaps/Mono.txt
ultraplot/cmaps/MonoCycle.txt
ultraplot/cmaps/NegPos.json
ultraplot-1.70.0.dist-info/licenses/LICENSE.txt
ultraplot-1.70.0.dist-info/METADATA
ultraplot-1.70.0.dist-info/WHEEL
ultraplot-1.70.0.dist-info/top_level.txt
ultraplot-1.70.0.dist-info/RECORD
