Metadata-Version: 2.4
Name: ultraplot
Version: 1.70.0
Summary: A succinct matplotlib wrapper for making beautiful, publication-quality graphics.
Author-email: Casper van Elteren <caspervanelteren@gmail.com>, Luke Davis <lukelbd@gmail.com>
Maintainer-email: Casper van Elteren <caspervanelteren@gmail.com>, "Matthew R. Becker" <becker.mr@gmail.com>
License: MIT
Project-URL: Documentation, https://ultraplot.readthedocs.io
Project-URL: Issue Tracker, https://github.com/ultraplot/ultraplot/issues
Project-URL: Source Code, https://github.com/ultraplot/ultraplot
Classifier: License :: OSI Approved :: MIT License
Classifier: Operating System :: OS Independent
Classifier: Intended Audience :: Science/Research
Classifier: Programming Language :: Python :: 3 :: Only
Classifier: Programming Language :: Python :: 3.10
Classifier: Programming Language :: Python :: 3.11
Classifier: Programming Language :: Python :: 3.12
Classifier: Programming Language :: Python :: 3.13
Classifier: Framework :: Matplotlib
Requires-Python: <3.14,>=3.10
License-File: LICENSE.txt
Requires-Dist: numpy>=1.26.0
Requires-Dist: matplotlib<3.11,>=3.9
Requires-Dist: typing-extensions; python_version < "3.12"
Dynamic: license-file
